{
  "images": {
    "ghcr.io/mentalsmash/ref-project-debdocker:nightly": {
      "schemaVersion": 2,
      "mediaType": "application/vnd.oci.image.index.v1+json",
      "manifests": [
        {
          "mediaType": "application/vnd.oci.image.manifest.v1+json",
          "digest": "sha256:c6daf9c2c2067e8f7cf580d98f69c9fca2a69562768726a76b515e49c41a294e",
          "size": 1494,
          "platform": {
            "architecture": "amd64",
            "os": "linux"
          }
        },
        {
          "mediaType": "application/vnd.oci.image.manifest.v1+json",
          "digest": "sha256:5888af82f3bcb84088df21cbef0d8a68d3fd51bf2e316553b4c7f9f87e8f6646",
          "size": 566,
          "annotations": {
            "vnd.docker.reference.digest": "sha256:c6daf9c2c2067e8f7cf580d98f69c9fca2a69562768726a76b515e49c41a294e",
            "vnd.docker.reference.type": "attestation-manifest"
          },
          "platform": {
            "architecture": "unknown",
            "os": "unknown"
          }
        }
      ],
      "annotations": {
        "org.opencontainers.image.created": "2024-04-26T02:45:32.389Z",
        "org.opencontainers.image.description": "Reference Implementation for a Debian/Docker Project",
        "org.opencontainers.image.licenses": "Apache-2.0",
        "org.opencontainers.image.revision": "3025cdba790205c831cc0bceecf15945ae30ad81",
        "org.opencontainers.image.source": "https://github.com/mentalsmash/ref-project-debdocker",
        "org.opencontainers.image.title": "ref-project-debdocker",
        "org.opencontainers.image.url": "https://github.com/mentalsmash/ref-project-debdocker",
        "org.opencontainers.image.version": "nightly"
      },
      "manifest_hash": "sha256:dc16b9e673229caecfd010f6a0a95a422430a6ca2410795ff944d85517cf9b96"
    },
    "mentalsmash/ref-project-debdocker:nightly": {
      "schemaVersion": 2,
      "mediaType": "application/vnd.oci.image.index.v1+json",
      "manifests": [
        {
          "mediaType": "application/vnd.oci.image.manifest.v1+json",
          "digest": "sha256:c6daf9c2c2067e8f7cf580d98f69c9fca2a69562768726a76b515e49c41a294e",
          "size": 1494,
          "platform": {
            "architecture": "amd64",
            "os": "linux"
          }
        },
        {
          "mediaType": "application/vnd.oci.image.manifest.v1+json",
          "digest": "sha256:5888af82f3bcb84088df21cbef0d8a68d3fd51bf2e316553b4c7f9f87e8f6646",
          "size": 566,
          "annotations": {
            "vnd.docker.reference.digest": "sha256:c6daf9c2c2067e8f7cf580d98f69c9fca2a69562768726a76b515e49c41a294e",
            "vnd.docker.reference.type": "attestation-manifest"
          },
          "platform": {
            "architecture": "unknown",
            "os": "unknown"
          }
        }
      ],
      "annotations": {
        "org.opencontainers.image.created": "2024-04-26T02:45:32.389Z",
        "org.opencontainers.image.description": "Reference Implementation for a Debian/Docker Project",
        "org.opencontainers.image.licenses": "Apache-2.0",
        "org.opencontainers.image.revision": "3025cdba790205c831cc0bceecf15945ae30ad81",
        "org.opencontainers.image.source": "https://github.com/mentalsmash/ref-project-debdocker",
        "org.opencontainers.image.title": "ref-project-debdocker",
        "org.opencontainers.image.url": "https://github.com/mentalsmash/ref-project-debdocker",
        "org.opencontainers.image.version": "nightly"
      },
      "manifest_hash": ""
    }
  },
  "layers": {
    "sha256:dc16b9e673229caecfd010f6a0a95a422430a6ca2410795ff944d85517cf9b96": [
      "ghcr.io/mentalsmash/ref-project-debdocker:nightly"
    ],
    "sha256:c6daf9c2c2067e8f7cf580d98f69c9fca2a69562768726a76b515e49c41a294e": [
      "mentalsmash/ref-project-debdocker:nightly",
      "ghcr.io/mentalsmash/ref-project-debdocker:nightly"
    ],
    "sha256:5888af82f3bcb84088df21cbef0d8a68d3fd51bf2e316553b4c7f9f87e8f6646": [
      "mentalsmash/ref-project-debdocker:nightly",
      "ghcr.io/mentalsmash/ref-project-debdocker:nightly"
    ]
  }
}