{
  "images": {
    "ghcr.io/mentalsmash/ref-project-debdocker:nightly": {
      "schemaVersion": 2,
      "mediaType": "application/vnd.oci.image.index.v1+json",
      "manifests": [
        {
          "mediaType": "application/vnd.oci.image.manifest.v1+json",
          "digest": "sha256:1d45b280a5062ea6a4c7c076514ec4cd54a1318086c48c77f5383ac638277d51",
          "size": 1494,
          "platform": {
            "architecture": "amd64",
            "os": "linux"
          }
        },
        {
          "mediaType": "application/vnd.oci.image.manifest.v1+json",
          "digest": "sha256:a80251412917b4557799f83377b149c1d3c26ef953040367cf028edab7214171",
          "size": 1494,
          "platform": {
            "architecture": "arm64",
            "os": "linux"
          }
        },
        {
          "mediaType": "application/vnd.oci.image.manifest.v1+json",
          "digest": "sha256:2629f9d186dea38d92977b16c6a5f6c18f8d53574ed52572473139592e55d60a",
          "size": 566,
          "annotations": {
            "vnd.docker.reference.digest": "sha256:1d45b280a5062ea6a4c7c076514ec4cd54a1318086c48c77f5383ac638277d51",
            "vnd.docker.reference.type": "attestation-manifest"
          },
          "platform": {
            "architecture": "unknown",
            "os": "unknown"
          }
        },
        {
          "mediaType": "application/vnd.oci.image.manifest.v1+json",
          "digest": "sha256:ae2478d5ab9d64c27abfd29311427b99a7c29da982ad860064d261b1651dfdc5",
          "size": 566,
          "annotations": {
            "vnd.docker.reference.digest": "sha256:a80251412917b4557799f83377b149c1d3c26ef953040367cf028edab7214171",
            "vnd.docker.reference.type": "attestation-manifest"
          },
          "platform": {
            "architecture": "unknown",
            "os": "unknown"
          }
        }
      ],
      "annotations": {
        "org.opencontainers.image.created": "2024-04-24T01:04:05.294Z",
        "org.opencontainers.image.description": "Reference Implementation for a Debian/Docker Project",
        "org.opencontainers.image.licenses": "Apache-2.0",
        "org.opencontainers.image.revision": "6415c67a45de922971dc2a7482d5275b4f64966d",
        "org.opencontainers.image.source": "https://github.com/mentalsmash/ref-project-debdocker",
        "org.opencontainers.image.title": "ref-project-debdocker",
        "org.opencontainers.image.url": "https://github.com/mentalsmash/ref-project-debdocker",
        "org.opencontainers.image.version": "nightly"
      }
    },
    "mentalsmash/ref-project-debdocker:nightly": {
      "schemaVersion": 2,
      "mediaType": "application/vnd.oci.image.index.v1+json",
      "manifests": [
        {
          "mediaType": "application/vnd.oci.image.manifest.v1+json",
          "digest": "sha256:1d45b280a5062ea6a4c7c076514ec4cd54a1318086c48c77f5383ac638277d51",
          "size": 1494,
          "platform": {
            "architecture": "amd64",
            "os": "linux"
          }
        },
        {
          "mediaType": "application/vnd.oci.image.manifest.v1+json",
          "digest": "sha256:a80251412917b4557799f83377b149c1d3c26ef953040367cf028edab7214171",
          "size": 1494,
          "platform": {
            "architecture": "arm64",
            "os": "linux"
          }
        },
        {
          "mediaType": "application/vnd.oci.image.manifest.v1+json",
          "digest": "sha256:2629f9d186dea38d92977b16c6a5f6c18f8d53574ed52572473139592e55d60a",
          "size": 566,
          "annotations": {
            "vnd.docker.reference.digest": "sha256:1d45b280a5062ea6a4c7c076514ec4cd54a1318086c48c77f5383ac638277d51",
            "vnd.docker.reference.type": "attestation-manifest"
          },
          "platform": {
            "architecture": "unknown",
            "os": "unknown"
          }
        },
        {
          "mediaType": "application/vnd.oci.image.manifest.v1+json",
          "digest": "sha256:ae2478d5ab9d64c27abfd29311427b99a7c29da982ad860064d261b1651dfdc5",
          "size": 566,
          "annotations": {
            "vnd.docker.reference.digest": "sha256:a80251412917b4557799f83377b149c1d3c26ef953040367cf028edab7214171",
            "vnd.docker.reference.type": "attestation-manifest"
          },
          "platform": {
            "architecture": "unknown",
            "os": "unknown"
          }
        }
      ],
      "annotations": {
        "org.opencontainers.image.created": "2024-04-24T01:04:05.294Z",
        "org.opencontainers.image.description": "Reference Implementation for a Debian/Docker Project",
        "org.opencontainers.image.licenses": "Apache-2.0",
        "org.opencontainers.image.revision": "6415c67a45de922971dc2a7482d5275b4f64966d",
        "org.opencontainers.image.source": "https://github.com/mentalsmash/ref-project-debdocker",
        "org.opencontainers.image.title": "ref-project-debdocker",
        "org.opencontainers.image.url": "https://github.com/mentalsmash/ref-project-debdocker",
        "org.opencontainers.image.version": "nightly"
      }
    }
  },
  "layers": {
    "sha256:1d45b280a5062ea6a4c7c076514ec4cd54a1318086c48c77f5383ac638277d51": [
      "mentalsmash/ref-project-debdocker:nightly",
      "ghcr.io/mentalsmash/ref-project-debdocker:nightly"
    ],
    "sha256:a80251412917b4557799f83377b149c1d3c26ef953040367cf028edab7214171": [
      "mentalsmash/ref-project-debdocker:nightly",
      "ghcr.io/mentalsmash/ref-project-debdocker:nightly"
    ],
    "sha256:2629f9d186dea38d92977b16c6a5f6c18f8d53574ed52572473139592e55d60a": [
      "mentalsmash/ref-project-debdocker:nightly",
      "ghcr.io/mentalsmash/ref-project-debdocker:nightly"
    ],
    "sha256:ae2478d5ab9d64c27abfd29311427b99a7c29da982ad860064d261b1651dfdc5": [
      "mentalsmash/ref-project-debdocker:nightly",
      "ghcr.io/mentalsmash/ref-project-debdocker:nightly"
    ]
  }
}